BridgeAccesslib/__init__.py
BridgeAccesslib/comm.py
BridgeAccesslib/extended_comm.py
BridgeAccesslib/data_convert/__init__.py
BridgeAccesslib/data_convert/chip_bitmap_pos.py
BridgeAccesslib/data_convert/data_swap.py
BridgeAccesslib-0.0.0.dist-info/METADATA
BridgeAccesslib-0.0.0.dist-info/WHEEL
BridgeAccesslib-0.0.0.dist-info/top_level.txt
BridgeAccesslib-0.0.0.dist-info/RECORD
